jetson_stats_node_exporter/__init__.py
jetson_stats_node_exporter/__main__.py
jetson_stats_node_exporter/exporter.py
jetson_stats_node_exporter/jtop_stats.py
jetson_stats_node_exporter/logger.py
jetson_stats_node_exporter-0.1.3.dist-info/licenses/LICENSE
jetson_stats_node_exporter-0.1.3.dist-info/METADATA
jetson_stats_node_exporter-0.1.3.dist-info/WHEEL
jetson_stats_node_exporter-0.1.3.dist-info/top_level.txt
jetson_stats_node_exporter-0.1.3.dist-info/RECORD
