Metadata-Version: 2.4
Name: jetson-stats-node-exporter
Version: 0.1.3
Summary: Prometheus Node Exporter for Nvidia Jetson Devices running Jetson Stats (now including AGX Orin with JetPack 6.0)
Author-email: Herbert Woisetschläger <herbert.woisetschlaeger@tum.de>
Classifier: License :: OSI Approved :: GNU Affero General Public License v3
Classifier: Programming Language :: Python :: 3
Classifier: Development Status :: 4 - Beta
Classifier: Intended Audience :: Science/Research
Classifier: Intended Audience :: Developers
Classifier: Environment :: GPU :: NVIDIA CUDA
Classifier: Topic :: System :: Monitoring
Requires-Python: >=3.10
License-File: LICENSE
Requires-Dist: jetson-stats==4.3.2
Requires-Dist: schedule==0.6.0
Requires-Dist: prometheus-client==0.21.1
Requires-Dist: psutil
Dynamic: license-file
